bemore/__init__.py
bemore/math.py
bemore-0.0.0.dist-info/licenses/LICENSE
bemore-0.0.0.dist-info/METADATA
bemore-0.0.0.dist-info/WHEEL
bemore-0.0.0.dist-info/top_level.txt
bemore-0.0.0.dist-info/RECORD
