Metadata-Version: 2.4
Name: bemore
Version: 0.0.0
Summary: A node-based editor
Author: Thomas Satterly
Author-email: nunya@biz.ness
License-Expression: MIT
Project-URL: Homepage, https://github.com/simple-all/bemore
Project-URL: Issues, https://github.com/simple-all/bemore/issues
Classifier: Programming Language :: Python :: 3
Classifier: Operating System :: OS Independent
Requires-Python: >=3.9
License-File: LICENSE
Dynamic: author-email
Dynamic: license-file
